pyudm-1.0.4.dist-info/licenses/LICENSE
udm/__init__.py
udm/commandline.py
udm/configs.py
udm/dependency.py
udm/main.py
udm/py.typed
pyudm-1.0.4.dist-info/METADATA
pyudm-1.0.4.dist-info/WHEEL
pyudm-1.0.4.dist-info/entry_points.txt
pyudm-1.0.4.dist-info/top_level.txt
pyudm-1.0.4.dist-info/RECORD
