Metadata-Version: 2.4
Name: pyudm
Version: 1.0.4
Summary: Unified Dependency Manager
Author-email: Marco Bascetta <m.bascetta@zohomail.eu>, Matteo Martelli <matteomartelli3@gmail.com>, Marco Melletti <melletti.marco@gmail.com>
Classifier: Programming Language :: Python :: 3
Classifier: Operating System :: OS Independent
Requires-Python: >=3.7
License-File: LICENSE
Requires-Dist: bpython==0.21
Requires-Dist: pyinstaller==4.5.1
Requires-Dist: argcomplete
Requires-Dist: wcwidth
Requires-Dist: bs4
Requires-Dist: lxml
Requires-Dist: rich
Requires-Dist: pyyaml
Requires-Dist: scm-wrap==1.1.30
Requires-Dist: typing_extensions
Dynamic: license-file
